etc42/__init__.py
etc42/etc42/Dockerfile
etc42/etc42/__init__.py
etc42/etc42/etc42.conf
etc42/etc42/etc42.py
etc42/tests/__init__.py
etc42/tests/test_etc42.py
etc42-1.0.1.dist-info/METADATA
etc42-1.0.1.dist-info/RECORD
etc42-1.0.1.dist-info/WHEEL
etc42-1.0.1.dist-info/entry_points.txt
etc42-1.0.1.dist-info/top_level.txt
