Metadata-Version: 2.1
Name: etc42
Version: 1.0.1
Summary: ETC42 Universal Exposure Time Calculator
Home-page: https://lam.fr/
Author: The LAM ETC42 developers
Author-email: UNKNOWN
License: GPLv3
Platform: UNKNOWN
Classifier: Development Status :: 1 - Planning
Classifier: Intended Audience :: Science/Research
Classifier: Operating System :: OS Independent
Classifier: Programming Language :: Python
Classifier: License :: OSI Approved :: GNU General Public License v3 or later (GPLv3+)
Classifier: Topic :: Scientific/Engineering :: Astronomy
Classifier: Topic :: Scientific/Engineering :: Physics
Requires-Dist: docker (>=2.0.0)
Requires-Dist: wget (>=1.0)
